[
  {
    "keyword": "Feature",
    "name": "Filter",
    "line": 1,
    "id": "filter",
    "tags": [],
    "uri": "features\\filter_by_name.feature",
    "elements": [
      {
        "id": "filter;p1-test-cases",
        "keyword": "Scenario",
        "line": 3,
        "name": "P1 Test Cases",
        "tags": [],
        "type": "scenario",
        "steps": [
          {
            "keyword": "Before",
            "hidden": true,
            "match": {
              "location": "features\\support\\hooks.js:102"
            },
            "result": {
              "status": "passed",
              "duration": 17824000000
            }
          },
          {
            "arguments": [],
            "keyword": "Given ",
            "line": 4,
            "name": "I open the website",
            "match": {
              "location": "features\\step_definitions\\filter_by_name_steps.js:4"
            },
            "result": {
              "status": "passed",
              "duration": 1549000000
            }
          },
          {
            "arguments": [],
            "keyword": "When ",
            "line": 7,
            "name": "I enter the computer name \"Acer Iconia\"",
            "match": {
              "location": "features\\step_definitions\\filter_by_name_steps.js:11"
            },
            "result": {
              "status": "passed",
              "duration": 759000000
            }
          },
          {
            "arguments": [],
            "keyword": "And ",
            "line": 8,
            "name": "User clicks on filer by name button",
            "match": {
              "location": "features\\step_definitions\\filter_by_name_steps.js:19"
            },
            "result": {
              "status": "passed",
              "duration": 572000000
            }
          },
          {
            "arguments": [],
            "keyword": "Then ",
            "line": 9,
            "name": "one result is retuened with name Acer Iconia",
            "match": {
              "location": "features\\step_definitions\\filter_by_name_steps.js:27"
            },
            "result": {
              "status": "passed",
              "duration": 94000000
            }
          },
          {
            "arguments": [],
            "keyword": "And ",
            "line": 12,
            "name": "enter an invalid computer name \"&*&*&*&\"",
            "match": {
              "location": "features\\step_definitions\\filter_by_name_steps.js:34"
            },
            "result": {
              "status": "passed",
              "duration": 593000000
            }
          },
          {
            "arguments": [],
            "keyword": "And ",
            "line": 13,
            "name": "user clicks search",
            "match": {
              "location": "features\\step_definitions\\filter_by_name_steps.js:41"
            },
            "result": {
              "status": "passed",
              "duration": 566000000
            }
          },
          {
            "arguments": [],
            "keyword": "Then ",
            "line": 14,
            "name": "no result should be retruned",
            "match": {
              "location": "features\\step_definitions\\filter_by_name_steps.js:49"
            },
            "result": {
              "status": "passed",
              "duration": 111000000
            }
          },
          {
            "arguments": [],
            "keyword": "And ",
            "line": 17,
            "name": "user clicks add new computer button",
            "match": {
              "location": "features\\step_definitions\\filter_by_name_steps.js:57"
            },
            "result": {
              "status": "passed",
              "duration": 529000000
            }
          },
          {
            "arguments": [],
            "keyword": "And ",
            "line": 18,
            "name": "enter a computer name \"test_computer\"",
            "match": {
              "location": "features\\step_definitions\\filter_by_name_steps.js:64"
            },
            "result": {
              "status": "passed",
              "duration": 806000000
            }
          },
          {
            "arguments": [],
            "keyword": "And ",
            "line": 19,
            "name": "enter Introduced Date \"2000-06-02\"",
            "match": {
              "location": "features\\step_definitions\\filter_by_name_steps.js:70"
            },
            "result": {
              "status": "passed",
              "duration": 691000000
            }
          },
          {
            "arguments": [],
            "keyword": "And ",
            "line": 20,
            "name": "enter Discontinued Date \"2022-06-01\"",
            "match": {
              "location": "features\\step_definitions\\filter_by_name_steps.js:76"
            },
            "result": {
              "status": "passed",
              "duration": 680000000
            }
          },
          {
            "arguments": [],
            "keyword": "And ",
            "line": 21,
            "name": "choose company",
            "match": {
              "location": "features\\step_definitions\\filter_by_name_steps.js:82"
            },
            "result": {
              "status": "passed",
              "duration": 564000000
            }
          },
          {
            "arguments": [],
            "keyword": "And ",
            "line": 22,
            "name": "create the computer",
            "match": {
              "location": "features\\step_definitions\\filter_by_name_steps.js:90"
            },
            "result": {
              "status": "passed",
              "duration": 2941000000
            }
          },
          {
            "arguments": [],
            "keyword": "Then ",
            "line": 23,
            "name": "successful computer creation",
            "match": {
              "location": "features\\step_definitions\\filter_by_name_steps.js:101"
            },
            "result": {
              "status": "passed",
              "duration": 96000000
            }
          },
          {
            "arguments": [],
            "keyword": "And ",
            "line": 26,
            "name": "go back to add computer page",
            "match": {
              "location": "features\\step_definitions\\filter_by_name_steps.js:108"
            },
            "result": {
              "status": "passed",
              "duration": 530000000
            }
          },
          {
            "arguments": [],
            "keyword": "And ",
            "line": 27,
            "name": "click add computer button",
            "match": {
              "location": "features\\step_definitions\\filter_by_name_steps.js:115"
            },
            "result": {
              "status": "passed",
              "duration": 3203000000
            }
          },
          {
            "arguments": [],
            "keyword": "Then ",
            "line": 28,
            "name": "validation of computer name mandatory message validation",
            "match": {
              "location": "features\\step_definitions\\filter_by_name_steps.js:147"
            },
            "result": {
              "status": "passed",
              "duration": 113000000
            }
          },
          {
            "keyword": "After",
            "hidden": true,
            "match": {
              "location": "features\\support\\hooks.js:120"
            },
            "result": {
              "status": "passed",
              "duration": 2000000
            }
          }
        ]
      }
    ]
  }
]